LICENSE
MANIFEST.in
README.rst
__init__.py
setup.py
dist/django_outbox_base_layout-1.2.tar.gz
django_outbox_base_layout.egg-info/PKG-INFO
django_outbox_base_layout.egg-info/SOURCES.txt
django_outbox_base_layout.egg-info/dependency_links.txt
django_outbox_base_layout.egg-info/top_level.txt
docs/.DS_Store
docs/examples/.DS_Store
docs/examples/templates/.DS_Store
docs/examples/templates/base_spartacus.html
docs/examples/templates/index.html
docs/examples/templates/sidebar_navbar.html
docs/examples/templates/top_navbar.html
outbox_base_layout/__init__.py
outbox_base_layout/admin.py
outbox_base_layout/apps.py
outbox_base_layout/models.py
outbox_base_layout/tests.py
outbox_base_layout/urls.py
outbox_base_layout/views.py
outbox_base_layout/__pycache__/__init__.cpython-36.pyc
outbox_base_layout/__pycache__/admin.cpython-36.pyc
outbox_base_layout/__pycache__/models.cpython-36.pyc
outbox_base_layout/__pycache__/urls.cpython-36.pyc
outbox_base_layout/__pycache__/views.cpython-36.pyc
outbox_base_layout/migrations/__init__.py
outbox_base_layout/migrations/__pycache__/__init__.cpython-36.pyc
outbox_base_layout/static/bower.json
outbox_base_layout/static/bower_components/bootstrap/.bower.json
outbox_base_layout/static/bower_components/bootstrap/Gruntfile.js
outbox_base_layout/static/bower_components/bootstrap/LICENSE
outbox_base_layout/static/bower_components/bootstrap/README.md
outbox_base_layout/static/bower_components/bootstrap/bower.json
outbox_base_layout/static/bower_components/bootstrap/package.js
outbox_base_layout/static/bower_components/bootstrap/package.json
outbox_base_layout/static/bower_components/bootstrap-social/.bower.json
outbox_base_layout/static/bower_components/bootstrap-social/.editorconfig
outbox_base_layout/static/bower_components/bootstrap-social/.gitignore
outbox_base_layout/static/bower_components/bootstrap-social/README.md
outbox_base_layout/static/bower_components/bootstrap-social/bootstrap-social.css
outbox_base_layout/static/bower_components/bootstrap-social/bootstrap-social.less
outbox_base_layout/static/bower_components/bootstrap-social/bootstrap-social.scss
outbox_base_layout/static/bower_components/bootstrap-social/bower.json
