Metadata-Version: 1.1
Name: django-outbox-base-layout
Version: 1.2
Summary: A simple Django app with a base layout for new projects of Outbox Company.
Home-page: https://www.outboxsistemas.com/
Author: Edson de Lima Cosme Junior
Author-email: edson.junior@outboxsistemas.com
License: BSD License
Platform: UNKNOWN
Classifier: Environment :: Web Environment
Classifier: Framework :: Django
Classifier: Framework :: Django :: 2.1
Classifier: Intended Audience :: Developers
Classifier: License :: OSI Approved :: BSD License
Classifier: Operating System :: OS Independent
Classifier: Programming Language :: Python
Classifier: Programming Language :: Python :: 3.5
Classifier: Programming Language :: Python :: 3.6
Classifier: Topic :: Internet :: WWW/HTTP
Classifier: Topic :: Internet :: WWW/HTTP :: Dynamic Content
